srblib/__init__.py
srblib/colour.py
srblib/debugger.py
srblib/dependency.py
srblib/email.py
srblib/file_importer.py
srblib/files.py
srblib/frozen.py
srblib/main.py
srblib/path.py
srblib/soup.py
srblib/srb_bank.py
srblib/srb_hash.py
srblib/srb_json.py
srblib/system.py
srblib/tabular.py
srblib/util.py
srblib-0.1.5.dist-info/LICENSE
srblib-0.1.5.dist-info/METADATA
srblib-0.1.5.dist-info/WHEEL
srblib-0.1.5.dist-info/entry_points.txt
srblib-0.1.5.dist-info/top_level.txt
srblib-0.1.5.dist-info/RECORD
