Metadata-Version: 2.1
Name: srblib
Version: 0.1.5
Summary: A python library by srb
Home-page: http://github.com/srbcheema1/srblib
Author: Sarbjit Singh
Author-email: srbcheema1@gmail.com
License: MIT License
Platform: UNKNOWN
Classifier: Operating System :: POSIX :: Linux
Classifier: License :: OSI Approved :: MIT License
Classifier: Programming Language :: Python :: 3.5
Requires-Dist: terminaltables
Requires-Dist: xlwt
Requires-Dist: xlrd
Requires-Dist: bs4
Requires-Dist: requests
Requires-Dist: argcomplete
